talos_aclient/__init__.py
talos_aclient/api_client.py
talos_aclient/api_response.py
talos_aclient/configuration.py
talos_aclient/exceptions.py
talos_aclient/py.typed
talos_aclient/rest.py
talos_aclient/api/__init__.py
talos_aclient/api/credentials_api.py
talos_aclient/api/dataset_api.py
talos_aclient/api/default_api.py
talos_aclient/api/graph_api.py
talos_aclient/api/model_api.py
talos_aclient/api/ontology_api.py
talos_aclient/api/resource_api.py
talos_aclient/api/segment_api.py
talos_aclient/api/task_api.py
talos_aclient/api/vector_api.py
talos_aclient/models/__init__.py
talos_aclient/models/add_hit_request.py
talos_aclient/models/add_resource_to_dataset_request.py
talos_aclient/models/add_segment_request.py
talos_aclient/models/add_segment_response.py
talos_aclient/models/add_task_request.py
talos_aclient/models/api_key_location.py
talos_aclient/models/app_talos_schema_dataset_get_resource_request.py
talos_aclient/models/app_talos_schema_dataset_graph_metadata.py
talos_aclient/models/app_talos_schema_graph_graph_metadata.py
talos_aclient/models/app_talos_schema_resource_get_resource_request.py
talos_aclient/models/app_talos_schema_resource_graph_metadata.py
talos_aclient/models/auth_api_key.py
talos_aclient/models/auth_basic.py
talos_aclient/models/auth_oauth2.py
talos_aclient/models/auth_type.py
talos_aclient/models/auto_context_config.py
talos_aclient/models/batch_add_dataset_resources_response.py
talos_aclient/models/batch_add_resources_to_dataset_request.py
talos_aclient/models/batch_add_segments_request.py
talos_aclient/models/batch_add_segments_response.py
talos_aclient/models/batch_extractor_config.py
talos_aclient/models/clean_config.py
talos_aclient/models/clone_dataset_request.py
talos_aclient/models/column.py
talos_aclient/models/community_detect_request.py
talos_aclient/models/community_detect_response.py
talos_aclient/models/condition_group.py
talos_aclient/models/config.py
talos_aclient/models/config1.py
talos_aclient/models/config2.py
talos_aclient-1.6.0.dist-info/METADATA
talos_aclient-1.6.0.dist-info/WHEEL
talos_aclient-1.6.0.dist-info/top_level.txt
talos_aclient-1.6.0.dist-info/RECORD
